odoo/addons/product_template_has_one_variant/README.rst
odoo/addons/product_template_has_one_variant/__init__.py
odoo/addons/product_template_has_one_variant/__manifest__.py
odoo/addons/product_template_has_one_variant/i18n/it.po
odoo/addons/product_template_has_one_variant/i18n/product_template_has_one_variant.pot
odoo/addons/product_template_has_one_variant/models/__init__.py
odoo/addons/product_template_has_one_variant/models/product_template.py
odoo/addons/product_template_has_one_variant/readme/CONTRIBUTORS.rst
odoo/addons/product_template_has_one_variant/readme/DESCRIPTION.rst
odoo/addons/product_template_has_one_variant/readme/USAGE.rst
odoo/addons/product_template_has_one_variant/static/description/icon.png
odoo/addons/product_template_has_one_variant/static/description/index.html
odoo/addons/product_template_has_one_variant/tests/__init__.py
odoo/addons/product_template_has_one_variant/tests/test_product_template.py
odoo/addons/product_template_has_one_variant/views/product_template.xml
odoo_addon_product_template_has_one_variant-16.0.1.0.1.3.dist-info/METADATA
odoo_addon_product_template_has_one_variant-16.0.1.0.1.3.dist-info/WHEEL
odoo_addon_product_template_has_one_variant-16.0.1.0.1.3.dist-info/top_level.txt
odoo_addon_product_template_has_one_variant-16.0.1.0.1.3.dist-info/RECORD
